odoo9_addon_oauth_provider_jwt-9.0.1.0.0-py2.7-nspkg.pth
odoo9_addon_oauth_provider_jwt-9.0.1.0.0.dist-info/DESCRIPTION.rst
odoo9_addon_oauth_provider_jwt-9.0.1.0.0.dist-info/METADATA
odoo9_addon_oauth_provider_jwt-9.0.1.0.0.dist-info/RECORD
odoo9_addon_oauth_provider_jwt-9.0.1.0.0.dist-info/WHEEL
odoo9_addon_oauth_provider_jwt-9.0.1.0.0.dist-info/metadata.json
odoo9_addon_oauth_provider_jwt-9.0.1.0.0.dist-info/namespace_packages.txt
odoo9_addon_oauth_provider_jwt-9.0.1.0.0.dist-info/top_level.txt
odoo_addons/oauth_provider_jwt/README.rst
odoo_addons/oauth_provider_jwt/__init__.py
odoo_addons/oauth_provider_jwt/__openerp__.py
odoo_addons/oauth_provider_jwt/controllers/__init__.py
odoo_addons/oauth_provider_jwt/controllers/main.py
odoo_addons/oauth_provider_jwt/models/__init__.py
odoo_addons/oauth_provider_jwt/models/oauth_provider_client.py
odoo_addons/oauth_provider_jwt/tests/__init__.py
odoo_addons/oauth_provider_jwt/tests/test_oauth_provider_json_web_token.py
odoo_addons/oauth_provider_jwt/views/oauth_provider_client.xml
